cgatcore/__init__.py
cgatcore/csv2db.py
cgatcore/csvutils.py
cgatcore/database.py
cgatcore/experiment.py
cgatcore/iotools.py
cgatcore/logfile.py
cgatcore/table.py
cgatcore/tables.py
cgatcore/version.py
cgatcore/pipeline/__init__.py
cgatcore/pipeline/cluster.py
cgatcore/pipeline/control.py
cgatcore/pipeline/database.py
cgatcore/pipeline/execution.py
cgatcore/pipeline/farm.py
cgatcore/pipeline/files.py
cgatcore/pipeline/parameters.py
cgatcore/pipeline/run_function.py
cgatcore/pipeline/utils.py
cgatcore/pipeline/wrappers.py
cgatcore/pipeline/logstash_formatter/__init__.py
cgatcore/remote/__init__.py
cgatcore/remote/aws.py
cgatcore/remote/azure.py
cgatcore/remote/ftp.py
cgatcore/remote/google_cloud.py
cgatcore/remote/sftp.py
cgatcore-0.6.15.dist-info/LICENSE
cgatcore-0.6.15.dist-info/METADATA
cgatcore-0.6.15.dist-info/WHEEL
cgatcore-0.6.15.dist-info/top_level.txt
cgatcore-0.6.15.dist-info/RECORD
