Metadata-Version: 2.1
Name: cgatcore
Version: 0.6.15
Summary: cgatcore : the Computational Genomics Analysis Toolkit
Home-page: https://github.com/cgat-developers/cgat-core
Author: Andreas Heger
Author-email: andreas.heger@gmail.com
License: MIT
Keywords: computational genomics
Platform: any
Classifier: Development Status :: 3 - Alpha
Classifier: Intended Audience :: Science/Research
Classifier: Intended Audience :: Developers
Classifier: License :: OSI Approved
Classifier: Programming Language :: Python
Classifier: Topic :: Software Development
Classifier: Topic :: Scientific/Engineering
Classifier: Operating System :: POSIX
Classifier: Operating System :: Unix
Classifier: Operating System :: MacOS
License-File: LICENSE
